superdirtpy/__init__.py
superdirtpy/chords.py
superdirtpy/euclid.py
superdirtpy/note.py
superdirtpy/params.py
superdirtpy/pattern.py
superdirtpy/py.typed
superdirtpy/scale.py
superdirtpy/scales.py
superdirtpy/superdirt_client.py
superdirtpy/temporal_context.py
superdirtpy/utils.py
superdirtpy-0.12.8.dist-info/LICENSE
superdirtpy-0.12.8.dist-info/METADATA
superdirtpy-0.12.8.dist-info/WHEEL
superdirtpy-0.12.8.dist-info/RECORD
