Metadata-Version: 2.1
Name: superdirtpy
Version: 0.12.8
Summary: superdirtpy is a python library for algorithmic composition working with SuperDirt.
Home-page: https://github.com/inaba1115
Author: inaba1115
Author-email: inaba1115@gmail.com
Requires-Python: >=3.12,<4.0
Classifier: Programming Language :: Python :: 3
Classifier: Programming Language :: Python :: 3.12
Requires-Dist: python-osc (>=1.8.3,<2.0.0)
Project-URL: Repository, https://github.com/inaba1115/superdirtpy
